stonks/__init__.py
stonks/main.py
stonks/stonks.py
stonks/version.py
stonks/tests/__init__.py
stonks/tests/test_chart_renderer.py
stonks/tests/test_data_fetcher.py
stonks/tests/test_data_manipulator.py
stonks-0.1.5.dist-info/METADATA
stonks-0.1.5.dist-info/WHEEL
stonks-0.1.5.dist-info/entry_points.txt
stonks-0.1.5.dist-info/top_level.txt
stonks-0.1.5.dist-info/RECORD
