Metadata-Version: 2.1
Name: stonks
Version: 0.1.5
Summary: stonks stonks stonks
Home-page: https://github.com/DanielLasota/Stonks
Author: Daniel Lasota
Author-email: grossmann.root@gmail.com
Classifier: Programming Language :: Python :: 3
Classifier: License :: OSI Approved :: MIT License
Classifier: Operating System :: OS Independent
Requires-Python: >=3.8, <3.9
Requires-Dist: pytest
Requires-Dist: pandas
Requires-Dist: yfinance
Requires-Dist: matplotlib
Requires-Dist: mplfinance
